pycaches/__init__.py
pycaches/cache.py
pycaches/decorators.py
pycaches/nohashmap.py
pycaches/policies.py
pycaches-0.0.7.dist-info/LICENSE.md
pycaches-0.0.7.dist-info/WHEEL
pycaches-0.0.7.dist-info/METADATA
pycaches-0.0.7.dist-info/RECORD
