Metadata-Version: 2.1
Name: pycaches
Version: 0.0.7
Summary: Python caching made easy
Home-page: https://github.com/codingjerk/pycaches
License: MIT
Author: Denis Gruzdev
Author-email: codingjerk@gmail.com
Requires-Python: >=3.7,<4.0
Classifier: License :: OSI Approved :: MIT License
Classifier: Programming Language :: Python :: 3
Classifier: Programming Language :: Python :: 3.7
Classifier: Programming Language :: Python :: 3.8
Classifier: Programming Language :: Python :: 3.9
Project-URL: Repository, https://github.com/codingjerk/pycaches
